hydra/__init__.py
hydra/app/__init__.py
hydra/app/ascan.py
hydra/app/atrace.py
hydra/app/call.py
hydra/app/cli.py
hydra/app/lstx.py
hydra/app/peerscan.py
hydra/app/test.py
hydra/app/top.py
hydra/app/txvio.py
hydra/hy.py
hydra/kc/__init__.py
hydra/kc/prices.py
hydra/log.py
hydra/res/.keep
hydra/rpc/__init__.py
hydra/rpc/base.py
hydra/rpc/explorer.py
hydra/rpc/hydra.py
hydra/test/__init__.py
hydra/test/__main__.py
hydra/test/app/__init__.py
hydra/test/app/__main__.py
hydra/test/app/cli.py
hydra/test/rpc.py
hydra/test/tests.py
hydra/util/__init__.py
hydra/util/asyncc.py
hydra/util/sha.py
hydra/util/struct.py
hydra/util/tlru.py
hydra_chain_py-2.8.0.dist-info/LICENSE
hydra_chain_py-2.8.0.dist-info/METADATA
hydra_chain_py-2.8.0.dist-info/WHEEL
hydra_chain_py-2.8.0.dist-info/entry_points.txt
hydra_chain_py-2.8.0.dist-info/RECORD
