Metadata-Version: 2.1
Name: hydra-chain-py
Version: 2.8.0
Summary: Hydra Chain Tools & Application Library.
Home-page: https://github.com/hydraverse/hypy
License: AGPLv3
Author: Phillip Sitbon
Author-email: phillip.sitbon@gmail.com
Requires-Python: >=3.11,<4.0
Classifier: License :: Other/Proprietary License
Classifier: Programming Language :: Python :: 3
Classifier: Programming Language :: Python :: 3.11
Requires-Dist: argcomplete (>=3.1.1,<4.0.0)
Requires-Dist: attrdict3 (>=2.0.2,<3.0.0)
Requires-Dist: currencies (>=2020.12.12,<2021.0.0)
Requires-Dist: pycryptodome (>=3.15.0,<4.0.0)
Requires-Dist: pytest (>=7.4.0,<8.0.0)
Requires-Dist: python-kucoin (>=2.1.3,<3.0.0)
Requires-Dist: pytz (>=2023.3,<2024.0)
Requires-Dist: requests (>=2.28.1,<3.0.0)
Project-URL: Repository, https://github.com/hydraverse/hypy
